nomad_camels_driver_zurich_instruments_mfli/zurich_instruments_mfli.py
nomad_camels_driver_zurich_instruments_mfli/zurich_instruments_mfli_ophyd.py
nomad_camels_driver_zurich_instruments_mfli-0.1.0.dist-info/LICENSE.txt
nomad_camels_driver_zurich_instruments_mfli-0.1.0.dist-info/METADATA
nomad_camels_driver_zurich_instruments_mfli-0.1.0.dist-info/WHEEL
nomad_camels_driver_zurich_instruments_mfli-0.1.0.dist-info/top_level.txt
nomad_camels_driver_zurich_instruments_mfli-0.1.0.dist-info/RECORD
