Metadata-Version: 2.1
Name: nomad_camels_driver_zurich_instruments_mfli
Version: 0.1.0
Summary: Basic instrument driver for the Zurich Instruments lock-in amplifier MFLI.
Author-email: Rouven Craemer <craemer.rouven@gmail.com>, Simon Sochiera <s.sochiera@web.de>
Project-URL: GitHub Page, https://github.com/FAU-LAP/CAMELS_drivers
Project-URL: Documentation, https://fau-lap.github.io/NOMAD-CAMELS
Requires-Python: >=3.11.3
License-File: LICENSE.txt
Requires-Dist: zhinst
